zeitig/__init__.py
zeitig/aggregates.py
zeitig/debug.py
zeitig/events.py
zeitig/reporting.py
zeitig/scripts.py
zeitig/sourcing.py
zeitig/store.py
zeitig/templates/console
zeitig/utils.py
zeitig-0.4.1.dist-info/entry_points.txt
zeitig-0.4.1.dist-info/LICENSE
zeitig-0.4.1.dist-info/WHEEL
zeitig-0.4.1.dist-info/METADATA
zeitig-0.4.1.dist-info/RECORD
