Metadata-Version: 2.1
Name: zeitig
Version: 0.4.1
Summary: time tracker and reporter
Home-page: https://github.com/diefans/zeitig
License: Apache-2.0
Keywords: t,i,m,e, ,t,r,a,c,k,e,r
Author: Oliver Berger
Author-email: diefans@gmail.com
Requires-Python: >=3.6,<4.0
Classifier: License :: OSI Approved :: Apache Software License
Classifier: Programming Language :: Python :: 3
Classifier: Programming Language :: Python :: 3.6
Classifier: Programming Language :: Python :: 3.7
Requires-Dist: click
Requires-Dist: colorama
Requires-Dist: crayons
Requires-Dist: dateparser
Requires-Dist: jinja2
Requires-Dist: pendulum
Requires-Dist: qtoml (>=0.2.4,<0.3.0)
Project-URL: Repository, https://github.com/diefans/zeitig
